Scylla.dll
pyscylla.cp38-win32.pyd
pyscylla-0.11.2.dist-info/LICENSE
pyscylla-0.11.2.dist-info/METADATA
pyscylla-0.11.2.dist-info/WHEEL
pyscylla-0.11.2.dist-info/top_level.txt
pyscylla-0.11.2.dist-info/RECORD
